trivial_tools/__init__.py
trivial_tools/calculations/__init__.py
trivial_tools/calculations/base_math.py
trivial_tools/checking/__init__.py
trivial_tools/checking/types.py
trivial_tools/checking/values.py
trivial_tools/classes/__init__.py
trivial_tools/classes/conservator.py
trivial_tools/classes/fluid.py
trivial_tools/classes/singleton_base.py
trivial_tools/config_handling/__init__.py
trivial_tools/config_handling/abstract_config.py
trivial_tools/config_handling/base_config.py
trivial_tools/config_handling/simple_config.py
trivial_tools/containers/__init__.py
trivial_tools/containers/class_carousel.py
trivial_tools/containers/class_de_carousel.py
trivial_tools/containers/class_moving_average.py
trivial_tools/containers/class_moving_sum.py
trivial_tools/containers/class_resampler.py
trivial_tools/datetime_tools/__init__.py
trivial_tools/datetime_tools/basic.py
trivial_tools/datetime_tools/coding.py
trivial_tools/datetime_tools/passed_time.py
trivial_tools/datetime_tools/text.py
trivial_tools/files/__init__.py
trivial_tools/files/json.py
trivial_tools/formatters/__init__.py
trivial_tools/formatters/base.py
trivial_tools/formatters/unfolds.py
trivial_tools/internet/__init__.py
trivial_tools/internet/requesting.py
trivial_tools/json_rpc/__init__.py
trivial_tools/json_rpc/basic_tools.py
trivial_tools/json_rpc/calls.py
trivial_tools/json_rpc/errors.py
trivial_tools/json_rpc/method_master.py
trivial_tools/pandas_tools/__init__.py
trivial_tools/pandas_tools/text.py
trivial_tools/runners/__init__.py
trivial_tools/runners/base.py
trivial_tools/special/__init__.py
trivial_tools/special/special.py
trivial_tools/storage/__init__.py
trivial_tools/storage/caching_instance.py
trivial_tools/storage/caching_machine.py
trivial_tools/system/__init__.py
trivial_tools/system/commit_info.py
trivial_tools/system/envs.py
trivial_tools/tests/__init__.py
trivial_tools/tests/test_fromatters.py
trivial_tools/tests/test_runners.py
trivial_tools/tests/calculations/__init__.py
trivial_tools-8.25.dist-info/LICENSE
trivial_tools-8.25.dist-info/METADATA
trivial_tools-8.25.dist-info/WHEEL
trivial_tools-8.25.dist-info/top_level.txt
trivial_tools-8.25.dist-info/RECORD
