Metadata-Version: 2.1
Name: trivial-tools
Version: 8.25
Summary: Trivial tools for various scripts
Home-page: https://github.com/IgorZyktin/trivial_tools
Author: Igor Zyktin
Author-email: nicord@yandex.ru
License: UNKNOWN
Platform: UNKNOWN
Classifier: Programming Language :: Python :: 3
Classifier: License :: OSI Approved :: MIT License
Classifier: Operating System :: OS Independent
Requires-Python: >=3.8
